{
  "Themes": [
    {
      "EntityName": "PowerAppsTheme",
      "ThemeName": "PowerAppsTheme"
    },
    {
      "EntityName": "PlatinumTheme",
      "ThemeName": "PlatinumTheme"
    },
    {
      "EntityName": "GreenTheme",
      "ThemeName": "GreenTheme"
    },
    {
      "EntityName": "OrangeTheme",
      "ThemeName": "OrangeTheme"
    },
    {
      "EntityName": "RedTheme",
      "ThemeName": "RedTheme"
    },
    {
      "EntityName": "SteelTheme",
      "ThemeName": "SteelTheme"
    }
  ]
}